hpcprocinfo.py
setup.py
hpcprocinfo.egg-info/PKG-INFO
hpcprocinfo.egg-info/SOURCES.txt
hpcprocinfo.egg-info/dependency_links.txt
hpcprocinfo.egg-info/entry_points.txt
hpcprocinfo.egg-info/requires.txt
hpcprocinfo.egg-info/top_level.txt