Metadata-Version: 1.1
Name: hpcprocinfo
Version: 1.0.0
Summary: script for checking the stats of HPC (cluster) processes
Home-page: https://github.com/goerz/hpcprocinfo
Author: Michael Goerz
Author-email: goerz@stanford.edu
License: GPL
Platform: UNKNOWN
Classifier: Development Status :: 4 - Beta
Classifier: Environment :: Console
Classifier: Intended Audience :: Science/Research
Classifier: License :: OSI Approved :: GNU General Public License v2 (GPLv2)
Classifier: Natural Language :: English
Classifier: Topic :: Scientific/Engineering
Classifier: Programming Language :: Python :: 2.7
Classifier: Programming Language :: Python :: 3.3
Classifier: Programming Language :: Python :: 3.4
